proy2/__init__.py
proy2-0.0.1.dist-info/LICENSE.txt
proy2-0.0.1.dist-info/METADATA
proy2-0.0.1.dist-info/WHEEL
proy2-0.0.1.dist-info/top_level.txt
proy2-0.0.1.dist-info/RECORD
