Metadata-Version: 2.1
Name: proy2
Version: 0.0.1
Summary: Demo2
Home-page: UNKNOWN
Author: Anksu Roy
Author-email: anksu101@gmail.com
License: UNKNOWN
Platform: UNKNOWN
Classifier: Programming Language :: Python :: 3
Classifier: Programming Language :: Python :: 3.5
Classifier: Programming Language :: Python :: 3.6
Classifier: Programming Language :: Python :: 3.7
Classifier: Programming Language :: Python :: 3.8
Classifier: License :: OSI Approved :: MIT License
Classifier: Operating System :: OS Independent
Requires-Dist: banglanltk
